data_sorter/__init__.py
data_sorter/old/AnImageASLUtility.py
data_sorter/old/AnImageDCMUtility.py
data_sorter/old/AnImageDataSorter.py
data_sorter/old/AnImageDataSorterGEeASL7.py
data_sorter/old/AnImageDataSorterGEpCASL13.py
data_sorter/old/AnImageDataSorterMISC.py
data_sorter/old/AnImageDataSorterPhilips13.py
data_sorter/old/AnImageDataSorterSiemens4.py
data_sorter/old/AnImageDataSorterSiemens5.py
data_sorter/old/AnImageDataSorterSiemensPASL.py
data_sorter/old/AnImageDataSorterSiemens_UCLA.py
data_sorter/old/AnImageDataSorterUtility.py
data_sorter/old/__init__.py
data_sorter/restructure/__init__.py
data_sorter/restructure/_dicom.py
data_sorter/restructure/_dicom_util.py
data_sorter/restructure/_type.py
data_sorter/restructure/data_sorter_base.py
data_sorter/restructure/dcm2nifti.py
data_sorter/restructure/errors.py
data_sorter/restructure/ge_3d_pcasl.py
data_sorter/restructure/ge_easl.py
data_sorter/restructure/noASL_MRI.py
data_sorter/restructure/philips_3d_pcasl.py
data_sorter/restructure/siemens_3d_pasl.py
data_sorter/restructure/siemens_3d_pcasl.py
data_sorter/restructure/siemens_3d_pcasl_old.py
data_sorter/restructure/uih_3d_pasl.py
animage_data_sorter-1.1.6.dist-info/METADATA
animage_data_sorter-1.1.6.dist-info/WHEEL
animage_data_sorter-1.1.6.dist-info/top_level.txt
animage_data_sorter-1.1.6.dist-info/RECORD
