Metadata-Version: 2.1
Name: animage-data-sorter
Version: 1.1.6
Summary: dicom sort
Home-page: https://gitee.com/AnImage-Beijing/data_sorter
Author: zhaomy
Author-email: zhaomy@an-image.cn
Classifier: Programming Language :: Python :: 3
Classifier: License :: OSI Approved :: MIT License
Classifier: Operating System :: OS Independent
